Workbook

Sheet Scenario Engine & Inputs
B2: Enterprise FP&A Scenario Engine - FY2026/2027 Projections
B4: Active Forecast Scenario Toggle: | C4: Base
B6: Macroeconomic & Financial Variable | C6: Bear / Conservative | D6: Base Case | E6: Bull / Aggressive | F6: Active Parameter Engine
B7: Enterprise Revenue Growth Rate (%) | C7: 0.085 | D7: 0.165 | E7: 0.28 | F7: =INDEX(C7:E7, 1, MATCH($C$4, $C$6:$E$6, 0))
B8: Cloud & Compute Infrastructure Inflation (%) | C8: 0.09 | D8: 0.045 | E8: 0.025 | F8: =INDEX(C8:E8, 1, MATCH($C$4, $C$6:$E$6, 0))
B9: General OPEX Cost Escalation (%) | C9: 0.07 | D9: 0.038 | E9: 0.02 | F9: =INDEX(C9:E9, 1, MATCH($C$4, $C$6:$E$6, 0))
B10: Headcount Expansion (Net New FTEs) | C10: 15 | D10: 45 | E10: 90 | F10: =INDEX(C10:E10, 1, MATCH($C$4, $C$6:$E$6, 0))
B11: Fully Loaded Annual Cost Per Hire ($) | C11: 145000 | D11: 135000 | E11: 128000 | F11: =INDEX(C11:E11, 1, MATCH($C$4, $C$6:$E$6, 0))
B12: Sales CAC / Marketing Spend Reinvestment Rate (%) | C12: 0.12 | D12: 0.18 | E12: 0.25 | F12: =INDEX(C12:E12, 1, MATCH($C$4, $C$6:$E$6, 0))
B13: Corporate Tax & Effective Interest Rate (%) | C13: 0.25 | D13: 0.21 | E13: 0.19 | F13: =INDEX(C13:E13, 1, MATCH($C$4, $C$6:$E$6, 0))

Sheet Enterprise P&L Projections
B2: Enterprise Income Statement (Multi-Year Scenario Model)
B5: Financial Statement Line Item ($ USD) | C5: FY2025 Actuals | D5: FY2026 Forecast | E5: FY2027 Pro-Forma | F5: YoY Variance ($) | G5: YoY Growth (%)
B6: Enterprise Gross Recurring Revenue | C6: 78500000 | D6: =C6*(1+'Scenario Engine & Inputs'!$F$7) | E6: =D6*(1+'Scenario Engine & Inputs'!$F$7) | F6: =D6-C6 | G6: =(D6-C6)/NULLIF(C6,0)
B7: COGS: Cloud Hosting & Infrastructure | C7: 14200000 | D7: =C7*(1+'Scenario Engine & Inputs'!$F$8) | E7: =D7*(1+'Scenario Engine & Inputs'!$F$8) | F7: =D7-C7 | G7: =(D7-C7)/NULLIF(C7,0)
B8: COGS: Direct Support & Customer Onboarding | C8: 6800000 | D8: =C8*(1+'Scenario Engine & Inputs'!$F$9) | E8: =D8*(1+'Scenario Engine & Inputs'!$F$9) | F8: =D8-C8 | G8: =(D8-C8)/NULLIF(C8,0)
B9: Total Cost of Goods Sold (COGS) | C9: =SUM(C7:C8) | D9: =SUM(D7:D8) | E9: =SUM(E7:E8) | F9: =D9-C9 | G9: =(D9-C9)/NULLIF(C9,0)
B10: Gross Profit | C10: =C6-C9 | D10: =D6-D9 | E10: =E6-E9 | F10: =D10-C10 | G10: =(D10-C10)/NULLIF(C10,0)
B11: Gross Margin % | C11: =C10/C6 | D11: =D10/D6 | E11: =E10/E6 | F11: =D11-C11 | G11: =D11-C11
B12: Operating Expenses (OPEX)
B13: R&D / Engineering Salaries & Tooling | C13: 22500000 | D13: =C13+('Scenario Engine & Inputs'!$F$10*'Scenario Engine & Inputs'!$F$11*0.55) | E13: =D13+('Scenario Engine & Inputs'!$F$10*'Scenario Engine & Inputs'!$F$11*0.55) | F13: =D13-C13 | G13: =(D13-C13)/NULLIF(C13,0)
B14: Sales & Marketing Acquisition | C14: 16800000 | D14: =C14*(1+'Scenario Engine & Inputs'!$F$12) | E14: =D14*(1+'Scenario Engine & Inputs'!$F$12) | F14: =D14-C14 | G14: =(D14-C14)/NULLIF(C14,0)
B15: General & Administrative (G&A) | C15: 7400000 | D15: =C15*(1+'Scenario Engine & Inputs'!$F$9) | E15: =D15*(1+'Scenario Engine & Inputs'!$F$9) | F15: =D15-C15 | G15: =(D15-C15)/NULLIF(C15,0)
B16: Total Operating Expenses | C16: =SUM(C13:C15) | D16: =SUM(D13:D15) | E16: =SUM(E13:E15) | F16: =D16-C16 | G16: =(D16-C16)/NULLIF(C16,0)
B17: EBITDA (Operating Income) | C17: =C10-C16 | D17: =D10-D16 | E17: =E10-E16 | F17: =D17-C17 | G17: =(D17-C17)/NULLIF(C17,0)
B18: EBITDA Margin % | C18: =C17/C6 | D18: =D17/D6 | E18: =E17/E6 | F18: =D18-C18 | G18: =D18-C18
B19: Depreciation & Amortization (D&A) | C19: 2100000 | D19: 2400000 | E19: 2700000 | F19: =D19-C19 | G19: =(D19-C19)/NULLIF(C19,0)
B20: EBIT (Operating Profit) | C20: =C17-C19 | D20: =D17-D19 | E20: =E17-E19 | F20: =D20-C20 | G20: =(D20-C20)/NULLIF(C20,0)
B21: Corporate Taxes & Interest Expense | C21: =C20*'Scenario Engine & Inputs'!$F$13 | D21: =D20*'Scenario Engine & Inputs'!$F$13 | E21: =E20*'Scenario Engine & Inputs'!$F$13 | F21: =D21-C21 | G21: =(D21-C21)/NULLIF(C21,0)
B22: Net Income | C22: =C20-C21 | D22: =D20-D21 | E22: =E20-E21 | F22: =D22-C22 | G22: =(D22-C22)/NULLIF(C22,0)
B23: Net Profit Margin % | C23: =C22/C6 | D23: =D22/D6 | E23: =E22/E6 | F23: =D23-C23 | G23: =D23-C23

Sheet EBITDA Sensitivity Matrix
B2: Two-Variable Enterprise EBITDA Stress Matrix ($ Millions)
B4: Active Model EBITDA Forecast: | D4: ='Enterprise P&L Projections'!$D$17
C7: Revenue Growth \ Cost Inf | D7: 0.02 | E7: 0.035 | F7: 0.05 | G7: 0.07 | H7: 0.09 | I7: 0.11
C8: 0.05 | D8: =(78500000*(1+C8)) - (21000000*(1+D$7)) - (46700000*(1+D$7*0.75)) | E8: =(78500000*(1+C8)) - (21000000*(1+E$7)) - (46700000*(1+E$7*0.75)) | F8: =(78500000*(1+C8)) - (21000000*(1+F$7)) - (46700000*(1+F$7*0.75)) | G8: =(78500000*(1+C8)) - (21000000*(1+G$7)) - (46700000*(1+G$7*0.75)) | H8: =(78500000*(1+C8)) - (21000000*(1+H$7)) - (46700000*(1+H$7*0.75)) | I8: =(78500000*(1+C8)) - (21000000*(1+I$7)) - (46700000*(1+I$7*0.75))
C9: 0.1 | D9: =(78500000*(1+C9)) - (21000000*(1+D$7)) - (46700000*(1+D$7*0.75)) | E9: =(78500000*(1+C9)) - (21000000*(1+E$7)) - (46700000*(1+E$7*0.75)) | F9: =(78500000*(1+C9)) - (21000000*(1+F$7)) - (46700000*(1+F$7*0.75)) | G9: =(78500000*(1+C9)) - (21000000*(1+G$7)) - (46700000*(1+G$7*0.75)) | H9: =(78500000*(1+C9)) - (21000000*(1+H$7)) - (46700000*(1+H$7*0.75)) | I9: =(78500000*(1+C9)) - (21000000*(1+I$7)) - (46700000*(1+I$7*0.75))
C10: 0.15 | D10: =(78500000*(1+C10)) - (21000000*(1+D$7)) - (46700000*(1+D$7*0.75)) | E10: =(78500000*(1+C10)) - (21000000*(1+E$7)) - (46700000*(1+E$7*0.75)) | F10: =(78500000*(1+C10)) - (21000000*(1+F$7)) - (46700000*(1+F$7*0.75)) | G10: =(78500000*(1+C10)) - (21000000*(1+G$7)) - (46700000*(1+G$7*0.75)) | H10: =(78500000*(1+C10)) - (21000000*(1+H$7)) - (46700000*(1+H$7*0.75)) | I10: =(78500000*(1+C10)) - (21000000*(1+I$7)) - (46700000*(1+I$7*0.75))
C11: 0.2 | D11: =(78500000*(1+C11)) - (21000000*(1+D$7)) - (46700000*(1+D$7*0.75)) | E11: =(78500000*(1+C11)) - (21000000*(1+E$7)) - (46700000*(1+E$7*0.75)) | F11: =(78500000*(1+C11)) - (21000000*(1+F$7)) - (46700000*(1+F$7*0.75)) | G11: =(78500000*(1+C11)) - (21000000*(1+G$7)) - (46700000*(1+G$7*0.75)) | H11: =(78500000*(1+C11)) - (21000000*(1+H$7)) - (46700000*(1+H$7*0.75)) | I11: =(78500000*(1+C11)) - (21000000*(1+I$7)) - (46700000*(1+I$7*0.75))
C12: 0.25 | D12: =(78500000*(1+C12)) - (21000000*(1+D$7)) - (46700000*(1+D$7*0.75)) | E12: =(78500000*(1+C12)) - (21000000*(1+E$7)) - (46700000*(1+E$7*0.75)) | F12: =(78500000*(1+C12)) - (21000000*(1+F$7)) - (46700000*(1+F$7*0.75)) | G12: =(78500000*(1+C12)) - (21000000*(1+G$7)) - (46700000*(1+G$7*0.75)) | H12: =(78500000*(1+C12)) - (21000000*(1+H$7)) - (46700000*(1+H$7*0.75)) | I12: =(78500000*(1+C12)) - (21000000*(1+I$7)) - (46700000*(1+I$7*0.75))
C13: 0.3 | D13: =(78500000*(1+C13)) - (21000000*(1+D$7)) - (46700000*(1+D$7*0.75)) | E13: =(78500000*(1+C13)) - (21000000*(1+E$7)) - (46700000*(1+E$7*0.75)) | F13: =(78500000*(1+C13)) - (21000000*(1+F$7)) - (46700000*(1+F$7*0.75)) | G13: =(78500000*(1+C13)) - (21000000*(1+G$7)) - (46700000*(1+G$7*0.75)) | H13: =(78500000*(1+C13)) - (21000000*(1+H$7)) - (46700000*(1+H$7*0.75)) | I13: =(78500000*(1+C13)) - (21000000*(1+I$7)) - (46700000*(1+I$7*0.75))
